{
  "schemaVersion": 1,
  "season": "2026-27",
  "updatedAt": "2026-07-16",
  "sources": [
    "https://www.premierleague.com/en/news/4673099/the-202627-premier-league-season-officially-starts",
    "https://en.wikipedia.org/wiki/2026%E2%80%9327_EFL_Championship",
    "https://en.wikipedia.org/wiki/2026%E2%80%9327_EFL_League_One",
    "https://en.wikipedia.org/wiki/2026%E2%80%9327_EFL_League_Two",
    "https://en.wikipedia.org/wiki/2026%E2%80%9327_Serie_A",
    "https://www.legab.it/seriebkt/classifica",
    "https://en.wikipedia.org/wiki/2026%E2%80%9327_Ligue_1",
    "https://en.wikipedia.org/wiki/2026%E2%80%9327_Ligue_2",
    "https://api.keukenkampioendivisie.nl/wp-content/uploads/2026/06/CONCEPT-Competitieprogramma-Keuken-Kampioen-Divisie-2026-27.pdf",
    "https://pzpn.pl/public/system/files/articles/13809/7378-Terminarz%20Betclic%201%20Ligi%202026-2027.pdf",
    "https://sfl.ch/articles/lescalendriersde-la-saison-202627",
    "https://spfl.co.uk/league/premiership",
    "https://en.wikipedia.org/wiki/2026%E2%80%9327_Scottish_Championship",
    "https://spfl.co.uk/league/league-one",
    "https://spfl.co.uk/league/league-two"
  ],
  "competitions": {
    "eng.premier-league": [
      "Arsenal",
      "Aston Villa",
      "Bournemouth",
      "Brentford",
      "Brighton & Hove Albion",
      "Chelsea",
      "Coventry City",
      "Crystal Palace",
      "Everton",
      "Fulham",
      "Hull City",
      "Ipswich Town",
      "Leeds United",
      "Liverpool",
      "Manchester City",
      "Manchester United",
      "Newcastle United",
      "Nottingham Forest",
      "Sunderland",
      "Tottenham Hotspur"
    ],
    "eng.championship": [
      "Birmingham City",
      "Blackburn Rovers",
      "Bolton Wanderers",
      "Bristol City",
      "Burnley",
      "Cardiff City",
      "Charlton Athletic",
      "Derby County",
      "Lincoln City",
      "Middlesbrough",
      "Millwall",
      "Norwich City",
      "Portsmouth",
      "Preston North End",
      "Queens Park Rangers",
      "Sheffield United",
      "Southampton",
      "Stoke City",
      "Swansea City",
      "Watford",
      "West Bromwich Albion",
      "West Ham United",
      "Wolverhampton Wanderers",
      "Wrexham"
    ],
    "eng.league-one": [
      "AFC Wimbledon",
      "Barnsley",
      "Blackpool",
      "Bradford City",
      "Bromley",
      "Burton Albion",
      "Cambridge United",
      "Doncaster Rovers",
      "Huddersfield Town",
      "Leicester City",
      "Leyton Orient",
      "Luton Town",
      "Mansfield Town",
      "Milton Keynes Dons",
      "Notts County",
      "Oxford United",
      "Peterborough United",
      "Plymouth Argyle",
      "Reading",
      "Sheffield Wednesday",
      "Stevenage",
      "Stockport County",
      "Wigan Athletic",
      "Wycombe Wanderers"
    ],
    "eng.league-two": [
      "Accrington Stanley",
      "Barnet",
      "Bristol Rovers",
      "Cheltenham Town",
      "Chesterfield",
      "Colchester United",
      "Crawley Town",
      "Crewe Alexandra",
      "Exeter City",
      "Fleetwood Town",
      "Gillingham",
      "Grimsby Town",
      "Newport County",
      "Northampton Town",
      "Oldham Athletic",
      "Port Vale",
      "Rochdale",
      "Rotherham United",
      "Salford City",
      "Shrewsbury Town",
      "Swindon Town",
      "Tranmere Rovers",
      "Walsall",
      "York City"
    ],
    "ita.serie-a": [
      "Atalanta",
      "Bologna",
      "Cagliari",
      "Como",
      "Fiorentina",
      "Frosinone",
      "Genoa",
      "Inter",
      "Juventus",
      "Lazio",
      "Lecce",
      "Milan",
      "Monza",
      "Napoli",
      "Parma",
      "Roma",
      "Sassuolo",
      "Torino",
      "Udinese",
      "Venezia"
    ],
    "ita.serie-b": [
      "Arezzo",
      "Ascoli",
      "Avellino",
      "Benevento",
      "Carrarese",
      "Catanzaro",
      "Cesena",
      "Cremonese",
      "Empoli",
      "Hellas Verona",
      "Juve Stabia",
      "L.R. Vicenza",
      "Mantova",
      "Modena",
      "Padova",
      "Palermo",
      "Pisa",
      "Sampdoria",
      "Südtirol",
      "Virtus Entella"
    ],
    "fra.ligue-1": [
      "Angers",
      "Auxerre",
      "Brest",
      "Le Havre",
      "Le Mans",
      "Lens",
      "Lille",
      "Lorient",
      "Lyon",
      "Marseille",
      "Monaco",
      "Nice",
      "Paris FC",
      "Paris Saint-Germain",
      "Rennes",
      "Strasbourg",
      "Toulouse",
      "Troyes"
    ],
    "fra.ligue-2": [
      "Annecy",
      "Boulogne",
      "Clermont",
      "Dijon",
      "Dunkerque",
      "Grenoble",
      "Guingamp",
      "Laval",
      "Metz",
      "Montpellier",
      "Nancy",
      "Nantes",
      "Pau",
      "Red Star",
      "Reims",
      "Rodez",
      "Saint-Étienne",
      "Sochaux"
    ],
    "ned.eerste-divisie": [
      "Almere City FC",
      "De Graafschap",
      "FC Den Bosch",
      "FC Dordrecht",
      "FC Eindhoven",
      "FC Emmen",
      "FC Volendam",
      "Helmond Sport",
      "Heracles Almelo",
      "Jong Ajax",
      "Jong AZ",
      "Jong FC Utrecht",
      "Jong PSV",
      "MVV Maastricht",
      "NAC Breda",
      "RKC Waalwijk",
      "Roda JC",
      "TOP Oss",
      "Vitesse",
      "VVV-Venlo"
    ],
    "pol.i-liga": [
      "Arka Gdynia",
      "Bruk-Bet Termalica Nieciecza",
      "Chrobry Głogów",
      "Lechia Gdańsk",
      "ŁKS Łódź",
      "Miedź Legnica",
      "Odra Opole",
      "Podbeskidzie Bielsko-Biała",
      "Pogoń Grodzisk Mazowiecki",
      "Pogoń Siedlce",
      "Polonia Bytom",
      "Polonia Warszawa",
      "Puszcza Niepołomice",
      "Ruch Chorzów",
      "Stal Mielec",
      "Stal Rzeszów",
      "Unia Skierniewice",
      "Warta Poznań"
    ],
    "sui.challenge-league": [
      "Etoile Carouge FC",
      "FC Aarau",
      "FC Rapperswil-Jona",
      "FC Stade Nyonnais",
      "FC Stade-Lausanne-Ouchy",
      "FC Wil 1900",
      "FC Winterthur",
      "Neuchâtel Xamax FCS",
      "SC Kriens",
      "Yverdon Sport FC"
    ],
    "sco.premiership": [
      "Aberdeen",
      "Celtic",
      "Dundee",
      "Dundee United",
      "Falkirk",
      "Heart of Midlothian",
      "Hibernian",
      "Kilmarnock",
      "Motherwell",
      "Rangers",
      "St Johnstone",
      "St Mirren"
    ],
    "sco.championship": [
      "Arbroath",
      "Ayr United",
      "Dunfermline Athletic",
      "Greenock Morton",
      "Inverness Caledonian Thistle",
      "Livingston",
      "Partick Thistle",
      "Queen's Park",
      "Raith Rovers",
      "Stenhousemuir"
    ],
    "sco.league-one": [
      "Airdrieonians",
      "Alloa Athletic",
      "Cove Rangers",
      "East Kilbride",
      "East Fife",
      "Hamilton Academical",
      "Montrose",
      "Peterhead",
      "Queen of the South",
      "Ross County"
    ],
    "sco.league-two": [
      "Annan Athletic",
      "Clyde",
      "Dumbarton",
      "Edinburgh City",
      "Elgin City",
      "Forfar Athletic",
      "Kelty Hearts",
      "Stirling Albion",
      "Stranraer",
      "The Spartans"
    ]
  }
}
